Metadata-Version: 2.4
Name: hnn-core
Version: 0.5.0
Summary: Code for biophysical simulation of a cortical column using Neuron
Home-page: 
Download-URL: http://github.com/jonescompneurolab/hnn-core
Maintainer: Mainak Jas
Maintainer-email: mainakjas@gmail.com
License: BSD (3-clause)
Platform: any
Classifier: Intended Audience :: Science/Research
Classifier: Intended Audience :: Developers
Classifier: License :: OSI Approved
Classifier: Programming Language :: Python
Classifier: Topic :: Software Development
Classifier: Topic :: Scientific/Engineering
Classifier: Operating System :: Microsoft :: Windows
Classifier: Operating System :: POSIX
Classifier: Operating System :: Unix
Classifier: Operating System :: MacOS
Classifier: Programming Language :: Python :: 3.9
Classifier: Programming Language :: Python :: 3.10
Classifier: Programming Language :: Python :: 3.11
Classifier: Programming Language :: Python :: 3.12
Classifier: Programming Language :: Python :: 3.13
Requires-Python: >=3.9, <3.14
License-File: LICENSE
Requires-Dist: numpy>=1.14
Requires-Dist: NEURON<=8.2.7,>=7.7; platform_system != "Windows"
Requires-Dist: matplotlib>=3.5.3
Requires-Dist: scipy
Requires-Dist: h5io
Provides-Extra: opt
Requires-Dist: scikit-learn; extra == "opt"
Provides-Extra: parallel
Requires-Dist: joblib; extra == "parallel"
Requires-Dist: psutil; extra == "parallel"
Provides-Extra: test
Requires-Dist: codespell; extra == "test"
Requires-Dist: pytest; extra == "test"
Requires-Dist: pytest-cov; extra == "test"
Requires-Dist: pytest-xdist; extra == "test"
Requires-Dist: ruff; extra == "test"
Provides-Extra: docs
Requires-Dist: mne; extra == "docs"
Requires-Dist: myst-parser; extra == "docs"
Requires-Dist: nibabel; extra == "docs"
Requires-Dist: numpydoc; extra == "docs"
Requires-Dist: pillow; extra == "docs"
Requires-Dist: pooch; extra == "docs"
Requires-Dist: pydata-sphinx-theme; extra == "docs"
Requires-Dist: sphinx; extra == "docs"
Requires-Dist: sphinx-gallery; extra == "docs"
Requires-Dist: sphinx-copybutton; extra == "docs"
Requires-Dist: tdqm; extra == "docs"
Provides-Extra: gui
Requires-Dist: ipywidgets>=8.0.0; extra == "gui"
Requires-Dist: ipykernel; extra == "gui"
Requires-Dist: ipympl; extra == "gui"
Requires-Dist: voila; extra == "gui"
Provides-Extra: dev
Requires-Dist: scikit-learn; extra == "dev"
Requires-Dist: joblib; extra == "dev"
Requires-Dist: psutil; extra == "dev"
Requires-Dist: codespell; extra == "dev"
Requires-Dist: pytest; extra == "dev"
Requires-Dist: pytest-cov; extra == "dev"
Requires-Dist: pytest-xdist; extra == "dev"
Requires-Dist: ruff; extra == "dev"
Requires-Dist: mne; extra == "dev"
Requires-Dist: myst-parser; extra == "dev"
Requires-Dist: nibabel; extra == "dev"
Requires-Dist: numpydoc; extra == "dev"
Requires-Dist: pillow; extra == "dev"
Requires-Dist: pooch; extra == "dev"
Requires-Dist: pydata-sphinx-theme; extra == "dev"
Requires-Dist: sphinx; extra == "dev"
Requires-Dist: sphinx-gallery; extra == "dev"
Requires-Dist: sphinx-copybutton; extra == "dev"
Requires-Dist: tdqm; extra == "dev"
Requires-Dist: ipywidgets>=8.0.0; extra == "dev"
Requires-Dist: ipykernel; extra == "dev"
Requires-Dist: ipympl; extra == "dev"
Requires-Dist: voila; extra == "dev"
Dynamic: classifier
Dynamic: description
Dynamic: description-content-type
Dynamic: download-url
Dynamic: license
Dynamic: license-file
Dynamic: maintainer
Dynamic: maintainer-email
Dynamic: platform
Dynamic: provides-extra
Dynamic: requires-dist
Dynamic: requires-python
Dynamic: summary
